shift_nth_row_n_steps/__init__.py
shift_nth_row_n_steps/__main__.py
shift_nth_row_n_steps/_main.py
shift_nth_row_n_steps/_torch_like.py
shift_nth_row_n_steps/cli.py
shift_nth_row_n_steps/py.typed
shift_nth_row_n_steps-1.0.0.dist-info/licenses/LICENSE
shift_nth_row_n_steps-1.0.0.dist-info/METADATA
shift_nth_row_n_steps-1.0.0.dist-info/WHEEL
shift_nth_row_n_steps-1.0.0.dist-info/entry_points.txt
shift_nth_row_n_steps-1.0.0.dist-info/top_level.txt
shift_nth_row_n_steps-1.0.0.dist-info/RECORD
