Metadata-Version: 2.4
Name: shift-nth-row-n-steps
Version: 1.0.0
Summary: Shift Nth row N steps in NumPy / PyTorch / TensorFlow / JAX
Author-email: 34j <34j.github@proton.me>
License: MIT
Project-URL: Bug Tracker, https://github.com/34j/shift-nth-row-n-steps/issues
Project-URL: Changelog, https://github.com/34j/shift-nth-row-n-steps/blob/main/CHANGELOG.md
Project-URL: documentation, https://shift-nth-row-n-steps.readthedocs.io
Project-URL: repository, https://github.com/34j/shift-nth-row-n-steps
Classifier: Development Status :: 2 - Pre-Alpha
Classifier: Intended Audience :: Developers
Classifier: Natural Language :: English
Classifier: Operating System :: OS Independent
Classifier: Programming Language :: Python :: 3.9
Classifier: Programming Language :: Python :: 3.10
Classifier: Programming Language :: Python :: 3.11
Classifier: Programming Language :: Python :: 3.12
Classifier: Programming Language :: Python :: 3.13
Classifier: Topic :: Software Development :: Libraries
Requires-Python: >=3.10
License-File: LICENSE
Requires-Dist: array-api-compat>=1.11.2
Requires-Dist: cm-time>=0.1.2
Requires-Dist: rich>=10
Requires-Dist: typer>=0.15
Requires-Dist: types-array-api>=1.1.3
Requires-Dist: typing-extensions>=4.14.0
Dynamic: license-file
